Workbook

Sheet Assumptions
A1: Assumptions & Levers
A2: Blue = editable input/lever. Adjust these and every scenario recalculates.
A3: Item | B3: Value | C3: Notes
A4: Stripe % fee | B4: 0.029 | C4: per transaction (standard)
A5: Stripe fixed fee | B5: 0.3 | C5: per transaction
A6: Infra cost / paid user / mo | B6: 0.3 | C6: hosting, DB, real-time sockets
A7: Support & overhead / paid user / mo | B7: 0.15 | C7: amortized support/ops
A9: AI usage per PAID user / month | C9: heavy-user estimate
A10: Tier 1 (card) gens | B10: 100 | C10: per user / month
A11: Tier 1 cost per gen | B11: 0.0012 | C11: premium model, ~3x Flash-Lite
A12: Tier 2 (lesson) gens | B12: 20 | C12: per user / month
A13: Tier 2 cost per gen | B13: 0.0024 | C13: premium model
A14: Tier 3 (unit) gens | B14: 2 | C14: per user / month
A15: Tier 3 cost per unit | B15: 0.015 | C15: staged pipeline
A16: AI cost / paid user / mo | B16: =B10*B11+B12*B13+B14*B15 -> 0.198 | C16: computed
A18: Competitor 'Pro' price / mo (reference) | B18: 5.59 | C18: Common Planner Pro
A19: Annual incentive: free months | B19: 2 | C19: annual = pay for (12 - this)

Sheet Scenarios
A1: Pricing Scenarios — profitable AND under Common Planner's $5.59
A2: Every scenario below undercuts their $5.59 AI plan. Green = live formulas from Assumptions.
A4: Plan | B4: AI? | C4: Billing | D4: Monthly list price | E4: Eff. monthly revenue | F4: Stripe fee /mo | G4: AI cost /mo | H4: Infra /mo | I4: Support /mo | J4: Total cost /mo | K4: Gross profit /mo | L4: Gross margin %
A5: Basic (no AI) | B5: No | C5: Monthly | D5: 2.99 | E5: =D5 -> 2.99 | F5: =E5*Assumptions!$B$4+Assumptions!$B$5 -> 0.38671 | G5: =IF(B5="Yes",Assumptions!$B$16,0) -> 0 | H5: =Assumptions!$B$6 -> 0.3 | I5: =Assumptions!$B$7 -> 0.15 | J5: =F5+G5+H5+I5 -> 0.83671 | K5: =E5-J5 -> 2.15329 | L5: =K5/E5 -> 0.72016388
A6: Basic (no AI) | B6: No | C6: Annual | D6: 2.99 | E6: =D6*(12-Assumptions!$B$19)/12 -> 2.4916667 | F6: =(E6*12*Assumptions!$B$4+Assumptions!$B$5)/12 -> 0.097258333 | G6: =IF(B6="Yes",Assumptions!$B$16,0) -> 0 | H6: =Assumptions!$B$6 -> 0.3 | I6: =Assumptions!$B$7 -> 0.15 | J6: =F6+G6+H6+I6 -> 0.54725833 | K6: =E6-J6 -> 1.9444083 | L6: =K6/E6 -> 0.78036455
A7: Plus (AI) — recommended | B7: Yes | C7: Monthly | D7: 4.99 | E7: =D7 -> 4.99 | F7: =E7*Assumptions!$B$4+Assumptions!$B$5 -> 0.44471 | G7: =IF(B7="Yes",Assumptions!$B$16,0) -> 0.198 | H7: =Assumptions!$B$6 -> 0.3 | I7: =Assumptions!$B$7 -> 0.15 | J7: =F7+G7+H7+I7 -> 1.09271 | K7: =E7-J7 -> 3.89729 | L7: =K7/E7 -> 0.78102004
A8: Plus (AI) — recommended | B8: Yes | C8: Annual | D8: 4.99 | E8: =D8*(12-Assumptions!$B$19)/12 -> 4.1583333 | F8: =(E8*12*Assumptions!$B$4+Assumptions!$B$5)/12 -> 0.14559167 | G8: =IF(B8="Yes",Assumptions!$B$16,0) -> 0.198 | H8: =Assumptions!$B$6 -> 0.3 | I8: =Assumptions!$B$7 -> 0.15 | J8: =F8+G8+H8+I8 -> 0.79359167 | K8: =E8-J8 -> 3.3647417 | L8: =K8/E8 -> 0.80915631
A9: Plus (AI) — aggressive | B9: Yes | C9: Monthly | D9: 3.99 | E9: =D9 -> 3.99 | F9: =E9*Assumptions!$B$4+Assumptions!$B$5 -> 0.41571 | G9: =IF(B9="Yes",Assumptions!$B$16,0) -> 0.198 | H9: =Assumptions!$B$6 -> 0.3 | I9: =Assumptions!$B$7 -> 0.15 | J9: =F9+G9+H9+I9 -> 1.06371 | K9: =E9-J9 -> 2.92629 | L9: =K9/E9 -> 0.73340602
A10: Plus (AI) — aggressive | B10: Yes | C10: Annual | D10: 3.99 | E10: =D10*(12-Assumptions!$B$19)/12 -> 3.325 | F10: =(E10*12*Assumptions!$B$4+Assumptions!$B$5)/12 -> 0.121425 | G10: =IF(B10="Yes",Assumptions!$B$16,0) -> 0.198 | H10: =Assumptions!$B$6 -> 0.3 | I10: =Assumptions!$B$7 -> 0.15 | J10: =F10+G10+H10+I10 -> 0.769425 | K10: =E10-J10 -> 2.555575 | L10: =K10/E10 -> 0.76859398
A11: Competitor Pro (AI) — ref | B11: Yes | C11: Monthly | D11: 5.59 | E11: =D11 -> 5.59 | F11: =E11*Assumptions!$B$4+Assumptions!$B$5 -> 0.46211 | G11: =IF(B11="Yes",Assumptions!$B$16,0) -> 0.198 | H11: =Assumptions!$B$6 -> 0.3 | I11: =Assumptions!$B$7 -> 0.15 | J11: =F11+G11+H11+I11 -> 1.11011 | K11: =E11-J11 -> 4.47989 | L11: =K11/E11 -> 0.80141145
A14: Key takeaways:
A15: • AI is only ~$0.20 / paid user / mo — cost is trivial. Stripe fees + infra dominate at low price points.
A16: • Annual billing amortizes Stripe's $0.30 fixed fee -> HIGHER margin % than monthly, even at a lower effective price. Push annual.
A17: • Plus (AI) at $4.99 undercuts their $5.59 AND includes unit-level AI generation they don't have, at ~78% gross margin.
A18: • Even the aggressive $3.99 AI tier holds ~73% margin. Room to compete on price if needed.
A19: • Margins here are GROSS (per-user variable). Fixed costs (salaries, marketing) are covered by volume — model those separately.
